crczp/topology_definition/__init__.py
crczp/topology_definition/image_naming.py
crczp/topology_definition/models.py
crczp/topology_definition/utils.py
crczp/topology_definition/validators.py
crczp_topology_definition-1.0.2.dist-info/METADATA
crczp_topology_definition-1.0.2.dist-info/WHEEL
crczp_topology_definition-1.0.2.dist-info/licenses/LICENSE
crczp_topology_definition-1.0.2.dist-info/RECORD
